testterpackage/__init__.py
testterpackage/functions.py
test_ter_package-0.1.0.dist-info/LICENSE
test_ter_package-0.1.0.dist-info/METADATA
test_ter_package-0.1.0.dist-info/WHEEL
test_ter_package-0.1.0.dist-info/top_level.txt
test_ter_package-0.1.0.dist-info/RECORD
