Metadata-Version: 2.1
Name: test-ter-package
Version: 0.1.0
Summary: Add your description here
Requires-Python: >=3.10
License-File: LICENSE
Requires-Dist: uv>=0.5.4
